protein_aa_analyze/__init__.py
protein_aa_analyze/analyzer.py
protein_aa_analyze-1.0.1.dist-info/LICENSE
protein_aa_analyze-1.0.1.dist-info/METADATA
protein_aa_analyze-1.0.1.dist-info/WHEEL
protein_aa_analyze-1.0.1.dist-info/entry_points.txt
protein_aa_analyze-1.0.1.dist-info/top_level.txt
protein_aa_analyze-1.0.1.dist-info/RECORD
