Metadata-Version: 2.1
Name: protein_aa_analyze
Version: 1.0.1
Summary: A simple Protein Amino-Acid Analyzer CLI application
Home-page: https://github.com/Imanjdd/protein_aa_analyze.git
Author: Iman Jouiad
Author-email: iman.jouiad@gmail.com
License: OSI Approved :: MIT License
Classifier: Programming Language :: Python :: 3
Classifier: License :: OSI Approved :: MIT License
Classifier: Operating System :: OS Independent
Requires-Python: >=3.6
License-File: LICENSE
